{
  "content": [
    {
      "is_image": true,
      "image": "/assets/saurfang-senjin.gif",
      "mobile_image": "/assets/WoWTaskerMinimized.png",
      "content_image": "/assets/WoWTaskerMinimized.png",
      "content_image_alt": "WoWTasker Logo",
      "image_alt": "Early Access gif",
      "title": "Early Access",
      "description": "Revolutionize your botting experience with WoW Tasker!",
      "button_text": null,
      "button_target_url": "/product-list"
    },
    {
      "is_image": true,
      "image": "/assets/orc-war.gif",
      "mobile_image": "/assets/WoWTaskerMinimized.png",
      "content_image": "/assets/WoWTaskerMinimized.png",
      "content_image_alt": "WoWTasker Logo",
      "image_alt": "Start Shopping gif",
      "title": "Start Shopping",
      "description": "WoW Tasker released the product that you need!",
      "button_text": "See Products",
      "button_target_url": "/product-list"
    }
  ]
}
